sorted_bag/__init__.py
sorted_bag/core.py
sorted_bag_avl-0.1.0.dist-info/licenses/LICENSE
sorted_bag_avl-0.1.0.dist-info/METADATA
sorted_bag_avl-0.1.0.dist-info/WHEEL
sorted_bag_avl-0.1.0.dist-info/top_level.txt
sorted_bag_avl-0.1.0.dist-info/RECORD
