Metadata-Version: 2.4
Name: sorted_bag_avl
Version: 0.1.0
Summary: A high-performance AVL-based Sorted Bag with Order Statistics
Home-page: https://github.com/Raghu-Pratap-Singh/Sorted-Bag-AVL
Author: Raghu Pratap Singh
Author-email: raghupratapsinghparmar@gmail.com
Classifier: Programming Language :: Python :: 3
Classifier: License :: OSI Approved :: MIT License
Classifier: Operating System :: OS Independent
Requires-Python: >=3.6
License-File: LICENSE
Dynamic: author
Dynamic: author-email
Dynamic: classifier
Dynamic: description-content-type
Dynamic: home-page
Dynamic: license-file
Dynamic: requires-python
Dynamic: summary
